np_monitor-0.1.2.dist-info/METADATA
np_monitor-0.1.2.dist-info/WHEEL
np_monitor/__init__.py
np_monitor/__main__.py
np_monitor/dxdiag.py
np_monitor/remote.py
np_monitor-0.1.2.dist-info/RECORD
